odoo/addons/account_payment_widget_amount/README.rst
odoo/addons/account_payment_widget_amount/__init__.py
odoo/addons/account_payment_widget_amount/__manifest__.py
odoo/addons/account_payment_widget_amount/i18n/account_payment_widget_amount.pot
odoo/addons/account_payment_widget_amount/i18n/pt.po
odoo/addons/account_payment_widget_amount/i18n/pt_BR.po
odoo/addons/account_payment_widget_amount/models/__init__.py
odoo/addons/account_payment_widget_amount/models/account_move_line.py
odoo/addons/account_payment_widget_amount/readme/CONTRIBUTORS.rst
odoo/addons/account_payment_widget_amount/readme/DESCRIPTION.rst
odoo/addons/account_payment_widget_amount/readme/USAGE.rst
odoo/addons/account_payment_widget_amount/static/description/icon.png
odoo/addons/account_payment_widget_amount/static/description/index.html
odoo/addons/account_payment_widget_amount/static/description/payment_widget.png
odoo/addons/account_payment_widget_amount/static/description/payment_widget_amount_reconciled.png
odoo/addons/account_payment_widget_amount/static/src/js/account_payment_field.js
odoo/addons/account_payment_widget_amount/static/src/xml/account_payment.xml
odoo/addons/account_payment_widget_amount/tests/__init__.py
odoo/addons/account_payment_widget_amount/tests/test_account_payment_widget_amount.py
odoo/addons/account_payment_widget_amount/views/account.xml
odoo12_addon_account_payment_widget_amount-12.0.1.0.0.99.dev9.dist-info/METADATA
odoo12_addon_account_payment_widget_amount-12.0.1.0.0.99.dev9.dist-info/WHEEL
odoo12_addon_account_payment_widget_amount-12.0.1.0.0.99.dev9.dist-info/top_level.txt
odoo12_addon_account_payment_widget_amount-12.0.1.0.0.99.dev9.dist-info/RECORD
